{"ohlc_bars": [{"openTime": "2026-03-23", "open": 2.02, "high": 2.04, "low": 1.93, "close": 2.03, "tickVolume": 65168382, "isOpen": false}, {"openTime": "2026-03-24", "open": 2.03, "high": 2.04, "low": 1.95, "close": 1.96, "tickVolume": 117423104, "isOpen": false}, {"openTime": "2026-03-25", "open": 1.98, "high": 1.99, "low": 1.95, "close": 1.96, "tickVolume": 35056669, "isOpen": false}, {"openTime": "2026-03-26", "open": 1.96, "high": 1.98, "low": 1.94, "close": 1.95, "tickVolume": 47782506, "isOpen": false}, {"openTime": "2026-03-27", "open": 1.95, "high": 1.97, "low": 1.9, "close": 1.9, "tickVolume": 49144623, "isOpen": false}, {"openTime": "2026-03-30", "open": 1.9, "high": 1.93, "low": 1.87, "close": 1.89, "tickVolume": 58691130, "isOpen": false}, {"openTime": "2026-03-31", "open": 1.9, "high": 1.92, "low": 1.88, "close": 1.91, "tickVolume": 40892069, "isOpen": false}, {"openTime": "2026-04-01", "open": 1.94, "high": 2.02, "low": 1.93, "close": 2.01, "tickVolume": 69868903, "isOpen": false}, {"openTime": "2026-04-02", "open": 1.98, "high": 2.02, "low": 1.98, "close": 2.0, "tickVolume": 36964105, "isOpen": false}, {"openTime": "2026-04-03", "open": 2.0, "high": 2.07, "low": 2.0, "close": 2.02, "tickVolume": 46817427, "isOpen": false}, {"openTime": "2026-04-06", "open": 2.03, "high": 2.06, "low": 2.03, "close": 2.04, "tickVolume": 18381158, "isOpen": false}, {"openTime": "2026-04-07", "open": 2.04, "high": 2.06, "low": 1.96, "close": 1.97, "tickVolume": 37202946, "isOpen": false}, {"openTime": "2026-04-08", "open": 2.03, "high": 2.09, "low": 2.03, "close": 2.08, "tickVolume": 37336304, "isOpen": false}, {"openTime": "2026-04-09", "open": 2.08, "high": 2.08, "low": 2.03, "close": 2.04, "tickVolume": 46475753, "isOpen": false}, {"openTime": "2026-04-10", "open": 2.05, "high": 2.1, "low": 2.05, "close": 2.08, "tickVolume": 34784975, "isOpen": false}, {"openTime": "2026-04-13", "open": 2.06, "high": 2.08, "low": 2.02, "close": 2.06, "tickVolume": 43211130, "isOpen": false}, {"openTime": "2026-04-14", "open": 2.07, "high": 2.1, "low": 2.07, "close": 2.09, "tickVolume": 27962302, "isOpen": false}, {"openTime": "2026-04-15", "open": 2.1, "high": 2.16, "low": 2.09, "close": 2.15, "tickVolume": 49291822, "isOpen": false}, {"openTime": "2026-04-16", "open": 2.17, "high": 2.2, "low": 2.12, "close": 2.14, "tickVolume": 33305039, "isOpen": false}, {"openTime": "2026-04-17", "open": 2.16, "high": 2.2, "low": 2.14, "close": 2.19, "tickVolume": 50829760, "isOpen": false}, {"openTime": "2026-04-20", "open": 2.18, "high": 2.19, "low": 2.15, "close": 2.15, "tickVolume": 37289953, "isOpen": false}, {"openTime": "2026-04-21", "open": 2.16, "high": 2.31, "low": 2.16, "close": 2.2, "tickVolume": 153633223, "isOpen": false}, {"openTime": "2026-04-22", "open": 2.22, "high": 2.25, "low": 2.16, "close": 2.18, "tickVolume": 66650848, "isOpen": false}, {"openTime": "2026-04-24", "open": 2.18, "high": 2.29, "low": 2.15, "close": 2.21, "tickVolume": 121863109, "isOpen": false}, {"openTime": "2026-04-27", "open": 2.23, "high": 2.26, "low": 2.21, "close": 2.23, "tickVolume": 59809649, "isOpen": false}, {"openTime": "2026-04-28", "open": 2.24, "high": 2.26, "low": 2.19, "close": 2.2, "tickVolume": 63049262, "isOpen": false}, {"openTime": "2026-04-29", "open": 2.23, "high": 2.31, "low": 2.19, "close": 2.27, "tickVolume": 80479998, "isOpen": false}, {"openTime": "2026-04-30", "open": 2.27, "high": 2.27, "low": 2.22, "close": 2.24, "tickVolume": 46475217, "isOpen": false}, {"openTime": "2026-05-04", "open": 2.25, "high": 2.27, "low": 2.16, "close": 2.17, "tickVolume": 88423903, "isOpen": false}, {"openTime": "2026-05-05", "open": 2.18, "high": 2.25, "low": 2.17, "close": 2.21, "tickVolume": 80326497, "isOpen": false}, {"openTime": "2026-05-06", "open": 2.23, "high": 2.26, "low": 2.21, "close": 2.25, "tickVolume": 67566786, "isOpen": false}, {"openTime": "2026-05-07", "open": 2.27, "high": 2.33, "low": 2.23, "close": 2.33, "tickVolume": 79970955, "isOpen": false}, {"openTime": "2026-05-08", "open": 2.35, "high": 2.36, "low": 2.31, "close": 2.32, "tickVolume": 75386275, "isOpen": false}, {"openTime": "2026-05-11", "open": 2.32, "high": 2.35, "low": 2.31, "close": 2.32, "tickVolume": 43060123, "isOpen": false}, {"openTime": "2026-05-12", "open": 2.33, "high": 2.35, "low": 2.21, "close": 2.21, "tickVolume": 76639902, "isOpen": false}, {"openTime": "2026-05-13", "open": 2.23, "high": 2.25, "low": 2.11, "close": 2.11, "tickVolume": 50349477, "isOpen": false}, {"openTime": "2026-05-14", "open": 2.12, "high": 2.15, "low": 2.12, "close": 2.13, "tickVolume": 36306749, "isOpen": false}, {"openTime": "2026-05-15", "open": 2.13, "high": 2.13, "low": 2.07, "close": 2.08, "tickVolume": 28238751, "isOpen": false}, {"openTime": "2026-05-18", "open": 2.08, "high": 2.09, "low": 2.02, "close": 2.03, "tickVolume": 28145052, "isOpen": false}, {"openTime": "2026-05-20", "open": 2.04, "high": 2.04, "low": 2.0, "close": 2.02, "tickVolume": 22684725, "isOpen": false}, {"openTime": "2026-05-21", "open": 2.04, "high": 2.04, "low": 1.93, "close": 1.93, "tickVolume": 29260615, "isOpen": false}, {"openTime": "2026-05-22", "open": 1.92, "high": 2.03, "low": 1.9, "close": 2.01, "tickVolume": 29325019, "isOpen": false}, {"openTime": "2026-05-25", "open": 2.02, "high": 2.04, "low": 2.01, "close": 2.04, "tickVolume": 20878167, "isOpen": false}, {"openTime": "2026-05-26", "open": 2.03, "high": 2.06, "low": 2.02, "close": 2.03, "tickVolume": 14183731, "isOpen": false}, {"openTime": "2026-05-27", "open": 2.03, "high": 2.03, "low": 2.03, "close": 2.03, "tickVolume": 0, "isOpen": false}, {"openTime": "2026-05-28", "open": 2.03, "high": 2.03, "low": 2.03, "close": 2.03, "tickVolume": 0, "isOpen": false}, {"openTime": "2026-05-29", "open": 2.03, "high": 2.03, "low": 2.03, "close": 2.03, "tickVolume": 0, "isOpen": false}, {"openTime": "2026-06-01", "open": 2.05, "high": 2.09, "low": 2.03, "close": 2.03, "tickVolume": 32365986, "isOpen": false}, {"openTime": "2026-06-02", "open": 1.56, "high": 1.6, "low": 1.56, "close": 1.58, "tickVolume": 49925901, "isOpen": false}, {"openTime": "2026-06-03", "open": 1.59, "high": 1.69, "low": 1.55, "close": 1.56, "tickVolume": 168413887, "isOpen": false}, {"openTime": "2026-06-04", "open": 1.56, "high": 1.59, "low": 1.53, "close": 1.54, "tickVolume": 77192481, "isOpen": false}, {"openTime": "2026-06-05", "open": 1.54, "high": 1.56, "low": 1.46, "close": 1.47, "tickVolume": 121595509, "isOpen": false}, {"openTime": "2026-06-08", "open": 1.47, "high": 1.51, "low": 1.44, "close": 1.45, "tickVolume": 152723443, "isOpen": false}, {"openTime": "2026-06-09", "open": 1.46, "high": 1.47, "low": 1.34, "close": 1.35, "tickVolume": 274090091, "isOpen": false}, {"openTime": "2026-06-10", "open": 1.35, "high": 1.36, "low": 1.26, "close": 1.26, "tickVolume": 152647915, "isOpen": false}, {"openTime": "2026-06-11", "open": 1.26, "high": 1.26, "low": 1.21, "close": 1.23, "tickVolume": 127600745, "isOpen": false}, {"openTime": "2026-06-12", "open": 1.24, "high": 1.25, "low": 1.21, "close": 1.21, "tickVolume": 214332904, "isOpen": false}, {"openTime": "2026-06-15", "open": 1.23, "high": 1.27, "low": 1.23, "close": 1.25, "tickVolume": 126492607, "isOpen": false}, {"openTime": "2026-06-16", "open": 1.25, "high": 1.3, "low": 1.23, "close": 1.24, "tickVolume": 160175285, "isOpen": false}, {"openTime": "2026-06-17", "open": 1.24, "high": 1.25, "low": 1.18, "close": 1.21, "tickVolume": 283319450, "isOpen": false}, {"openTime": "2026-06-18", "open": 1.22, "high": 1.26, "low": 1.2, "close": 1.23, "tickVolume": 182878905, "isOpen": false}, {"openTime": "2026-06-19", "open": 1.22, "high": 1.23, "low": 1.2, "close": 1.2, "tickVolume": 89809881, "isOpen": false}, {"openTime": "2026-06-22", "open": 1.23, "high": 1.32, "low": 1.22, "close": 1.32, "tickVolume": 73042288, "isOpen": false}, {"openTime": "2026-06-23", "open": 1.37, "high": 1.45, "low": 1.31, "close": 1.31, "tickVolume": 772990350, "isOpen": false}], "updated": 1782221314.0054603}